src/common/fp_recomposer.v
// src/common/fp_recomposer.v
// 功能：将最终计算好的符号、指数场和尾数场组合为64位双精度浮点数。
// 职责：纯粹的位拼接，所有关于上溢/下溢/规格化的决策都在上游模块完成。

`default_nettype none

module fp_recomposer (
    input  wire        final_sign,          // 最终的符号位
    input  wire [10:0] final_exponent_field, // 最终的11位指数场 (已编码)
    input  wire [51:0] final_mantissa_field, // 最终的52位尾数场
    
    // 特殊值标志，由上游逻辑计算得出
    input  wire        is_nan_out,
    input  wire        is_inf_out,
    input  wire        is_zero_out,
    
    output wire [63:0] fp_out               // 输出的64位浮点数
);

    // 组合逻辑非常直接：
    // 1. 检查是否为 NaN
    // 2. 检查是否为无穷大
    // 3. 检查是否为零 (当符号位为1时，可以正确生成 -0)
    // 4. 如果都不是，则按正常方式组合符号、指数和尾数。
    //    此时，(指数场, 尾数场) 的组合已经可以正确表示规格化数、非规格化数。
    //    例如: (00...0,非零) -> 非规格化数, (非0非FF, 任意) -> 规格化数

    assign fp_out =  (is_nan_out)  ? 64'h7FF8000000000001 :      // 输出一个标准的 Quiet NaN
                     (is_inf_out)  ? {final_sign, 11'h7FF, 52'h0} :
                     (is_zero_out) ? {final_sign, 11'h000, 52'h0} :
                     /* 正常组合 */ {final_sign, final_exponent_field, final_mantissa_field};

endmodule

`default_nettype wire

src/common/fp_rounder.v
// src/common/fp_rounder.v
// 功能：根据G, R, S位实现平衡型舍入(Round to Nearest, Ties to Even)

`default_nettype none

module fp_rounder (
    input  wire [52:0] mant_in,      // 输入的53位尾数 (规格化后的)
    input  wire        g,            // Guard bit
    input  wire        r,            // Round bit
    input  wire        s,            // Sticky bit

    output wire [52:0] mant_out,     // 舍入后的53位尾数
    output wire        carry_out     // 舍入后产生的进位 (例如 1.11...1 + 1 -> 10.00...0)
);

    wire round_decision;
    wire lsb = mant_in[0]; // 待舍入的尾数的最低位

    // 平衡型舍入决策逻辑
    // 当丢弃部分 > 0.5 LSB 时，或
    // 当丢弃部分 = 0.5 LSB 且尾数最低位为1时，向上舍入
    assign round_decision = g & (r | s | lsb);

    // 执行舍入操作：将决策位加到尾数上
    // 使用54位加法器以捕获可能的进位
    wire [53:0] rounded_result;
    assign rounded_result = {1'b0, mant_in} + round_decision;

    // 输出结果
    assign mant_out = rounded_result[52:0];
    assign carry_out = rounded_result[53];

endmodule

`default_nettype wire

src/common/fp_decomposer.v
// src/common/fp_decomposer.v
// 功能：将64位双精度浮点数分解为符号、指数、尾数及特殊标志位

`default_nettype none

module fp_decomposer (
    input  wire [63:0] fp_in,          // 输入的64位浮点数

    output wire        sign,           // 符号位
    output wire signed [11:0] exponent,       // 12位指数 (含符号，为方便计算)
    output wire [52:0] mantissa,       // 53位尾数 (规格化数含隐藏位'1', 非规格化数含'0')
    
    output wire        is_nan,         // 是不是NaN
    output wire        is_inf,         // 是不是无穷大
    output wire        is_zero,        // 是不是零
    output wire        is_denormalized // 是不是非规格化数
);

    // 1. 直接从输入中拆分字段
    wire        raw_sign      = fp_in[63];
    wire [10:0] raw_exponent  = fp_in[62:52];
    wire [51:0] raw_mantissa  = fp_in[51:0];

    // 2. 定义特殊指数值
    localparam EXP_ALL_ZEROS = 11'h000;
    localparam EXP_ALL_ONES  = 11'h7FF;
    localparam EXP_BIAS      = 1023;

    // 3. 判断特殊类型
    wire is_special_exp = (raw_exponent == EXP_ALL_ZEROS) || (raw_exponent == EXP_ALL_ONES);
    wire is_mantissa_zero = (raw_mantissa == 52'h0);

    // is_nan: exp全1, mantissa非0. [3, 4]
    assign is_nan = (raw_exponent == EXP_ALL_ONES) && (!is_mantissa_zero);
    
    // is_inf: exp全1, mantissa为0. [3, 4]
    assign is_inf = (raw_exponent == EXP_ALL_ONES) && (is_mantissa_zero);
    
    // is_zero: exp全0, mantissa为0. [4]
    assign is_zero = (raw_exponent == EXP_ALL_ZEROS) && (is_mantissa_zero);
    
    // is_denormalized: exp全0, mantissa非0. [4]
    assign is_denormalized = (raw_exponent == EXP_ALL_ZEROS) && (!is_mantissa_zero);

    // 4. 计算输出
    assign sign = raw_sign;

    // 指数计算：
    // - 规格化数: 实际指数 = 偏移指数 - 偏移量
    // - 非规格化数: 实际指数固定为 1 - 偏移量 = -1022
    // - 特殊值: 指数可以设为0，因为会被is_nan/is_inf标志处理
    assign exponent = (is_denormalized)   ? (1 - EXP_BIAS) :          // 非规格化数，指数为 1-1023 = -1022
                    (is_special_exp)   ? 12'd0 :                   // 特殊值 (Inf, NaN)，指数可为0
                                     (raw_exponent - EXP_BIAS);  // 规格化数


    // 尾数计算：
    // - 规格化数: 尾数 = {1'b1, raw_mantissa}
    // - 非规格化数: 尾数 = {1'b0, raw_mantissa}
    // - 特殊值(0, inf, nan): 尾数可以为0，由标志位处理
    assign mantissa = (is_denormalized) ? {1'b0, raw_mantissa} : 
                      (is_special_exp) ? 53'd0 : 
                                         {1'b1, raw_mantissa};            
endmodule

`default_nettype wire

src/fp_div.v
`default_nettype none
module fp_div (
    input  wire        clk,
    input  wire        rst_n,
    input  wire        start,
    input  wire [63:0] fp_a,
    input  wire [63:0] fp_b,

    output reg  [63:0] fp_out,
    output reg         done,
    output reg         overflow,
    output reg         underflow,
    output reg         invalid
);

    // ... (实例化分解模块部分) ...
    wire        sign_a, sign_b;
    wire signed [11:0] exp_a, exp_b;
    wire [52:0] man_a, man_b;
    wire        is_nan_a, is_inf_a, is_zero_a, is_denorm_a;
    wire        is_nan_b, is_inf_b, is_zero_b, is_denorm_b;

    // 假设 fp_decomposer 存在于项目中
    fp_decomposer u_dec_a (
        .fp_in(fp_a), .sign(sign_a), .exponent(exp_a), .mantissa(man_a),
        .is_nan(is_nan_a), .is_inf(is_inf_a), .is_zero(is_zero_a), .is_denormalized(is_denorm_a)
    );

    fp_decomposer u_dec_b (
        .fp_in(fp_b), .sign(sign_b), .exponent(exp_b), .mantissa(man_b),
        .is_nan(is_nan_b), .is_inf(is_inf_b), .is_zero(is_zero_b), .is_denormalized(is_denorm_b)
    );

    localparam S_IDLE       = 3'd0;
    localparam S_PREPARE    = 3'd1;
    localparam S_DIVIDE     = 3'd2;
    localparam S_NORMALIZE  = 3'd3;
    localparam S_ROUND      = 3'd4;
    localparam S_PACK       = 3'd5;
    localparam S_DONE       = 3'd6;

    reg [2:0] state;

    reg [109:0] remainder_reg;
    reg [55:0]  quotient_reg;
    reg [5:0]   div_cnt;
    
    reg        res_sign;
    reg signed [13:0] res_exp;
    reg [52:0] res_man;
    
    reg res_is_nan;
    reg res_is_inf;
    reg res_is_zero;

    reg [53:0] divisor_core; 

    wire calc_sign = sign_a ^ sign_b;
    wire is_invalid_op = (is_zero_a && is_zero_b) || (is_inf_a && is_inf_b);
    wire check_nan = is_nan_a || is_nan_b || is_invalid_op;
    wire check_inf = (is_inf_a && !is_inf_b) || (!is_nan_a && !is_inf_a && !is_zero_a && is_zero_b);
    wire check_zero = (is_zero_a && !is_zero_b && !is_nan_b) || (!is_inf_a && !is_nan_a && is_inf_b);

    // =============================================================
    // 实例化 fp_rounder 模块 logic
    // =============================================================
    wire [52:0] rounder_mant_in;
    wire        rounder_g;
    wire        rounder_r;
    wire        rounder_s;
    wire [52:0] rounder_mant_out;
    wire        rounder_carry;

    // quotient_reg 在 S_NORMALIZE 之后是 [55:0]
    // [55] 是隐藏位 (1)
    // [54:3] 是小数部分 (52位) -> 合计 [55:3] 为 53 位 Mantissa
    // [2] 是 Guard bit
    // [1] 是 Round bit
    // [0] 是 Sticky bit 的一部分 (还需要结合 remainder)
    
    assign rounder_mant_in = quotient_reg[55:3];
    assign rounder_g       = quotient_reg[2];
    assign rounder_r       = quotient_reg[1];
    // Sticky bit: 当前商的最低位 OR 余数是否非零
    assign rounder_s       = quotient_reg[0] | (|remainder_reg);

    fp_rounder u_rounder (
        .mant_in   (rounder_mant_in),
        .g         (rounder_g),
        .r         (rounder_r),
        .s         (rounder_s),
        .mant_out  (rounder_mant_out),
        .carry_out (rounder_carry)
    );
    // =============================================================

    always @(posedge clk or negedge rst_n) begin
        if (!rst_n) begin
            state <= S_IDLE;
            fp_out <= 64'b0;
            done <= 1'b0;
            overflow <= 1'b0;
            underflow <= 1'b0;
            invalid <= 1'b0;
            
            remainder_reg <= 0;
            quotient_reg <= 0;
            div_cnt <= 0;
            divisor_core <= 0;
            
            res_sign <= 0;
            res_exp <= 0;
            res_man <= 0;
            res_is_nan <= 0;
            res_is_inf <= 0;
            res_is_zero <= 0;
            
        end else begin
            done <= 1'b0; 

            case (state)
                S_IDLE: begin
                    if (start) begin
                        state <= S_PREPARE;
                        overflow <= 1'b0;
                        underflow <= 1'b0;
                        invalid <= 1'b0;
                    end
                end

                S_PREPARE: begin
                    res_sign <= calc_sign;
                    if (check_nan) begin
                        res_is_nan <= 1'b1;
                        res_is_inf <= 1'b0;
                        res_is_zero <= 1'b0;
                        invalid <= is_invalid_op;
                        state <= S_PACK;
                    end
                    else if (check_inf) begin
                        res_is_nan <= 1'b0;
                        res_is_inf <= 1'b1;
                        res_is_zero <= 1'b0;
                        if (is_zero_b) overflow <= 1'b1;
                        state <= S_PACK;
                    end
                    else if (check_zero) begin
                        res_is_nan <= 1'b0;
                        res_is_inf <= 1'b0;
                        res_is_zero <= 1'b1;
                        state <= S_PACK;
                    end
                    else begin
                        res_is_nan <= 1'b0;
                        res_is_inf <= 1'b0;
                        res_is_zero <= 1'b0;
                        res_exp <= $signed(exp_a) - $signed(exp_b);
                        // 预留足够位数用于除法
                        remainder_reg <= {1'b0, man_a, 56'b0}; 
                        divisor_core <= {1'b0, man_b};
                        quotient_reg <= 56'd0;
                        div_cnt <= 6'd56; 
                        state <= S_DIVIDE;
                    end
                end

                S_DIVIDE: begin
                    if (remainder_reg[109:56] >= divisor_core) begin
                         // 够减
                         remainder_reg <= { (remainder_reg[109:56] - divisor_core), remainder_reg[55:0] } << 1;
                         quotient_reg <= {quotient_reg[54:0], 1'b1};
                    end else begin
                         remainder_reg <= remainder_reg << 1;
                         quotient_reg <= {quotient_reg[54:0], 1'b0};
                    end

                    div_cnt <= div_cnt - 1'b1;
                    if (div_cnt == 1) begin
                        state <= S_NORMALIZE;
                    end
                end

                S_NORMALIZE: begin
                    // 标准化商，确保第55位是1
                    if (quotient_reg[55]) begin
                        // 已规格化
                    end else begin
                        quotient_reg <= {quotient_reg[54:0], 1'b0};
                        res_exp <= res_exp - 1'b1;
                    end
                    state <= S_ROUND;
                end

                S_ROUND: begin
                    // 使用 fp_rounder 的输出
                    // 如果产生 carry_out，说明尾数 1.11...1 + 1 变成了 10.00...0
                    // 此时 rounder_mant_out 通常变为 0，我们需要增加指数
                    
                    if (rounder_carry) begin
                        res_man <= 53'b0; // 实际值是 10.0...，recomposer取低52位为0
                        res_exp <= res_exp + 1'sd1;
                    end else begin
                        res_man <= rounder_mant_out;
                    end
                    
                    state <= S_PACK;
                end

                S_PACK: begin
                    if (!res_is_nan && !res_is_inf && !res_is_zero) begin
                        if (res_exp > 1023) begin
                            overflow <= 1'b1;
                            res_is_inf <= 1'b1;
                        end else if (res_exp < -1022) begin
                            underflow <= 1'b1;
                            res_is_zero <= 1'b1;
                            res_exp <= 0;
                        end
                    end
                    state <= S_DONE;
                end
                
                S_DONE: begin
                    done <= 1'b1;
                    state <= S_IDLE;
                end
            endcase
        end
    end

    wire [10:0] final_exp_field;
    assign final_exp_field = (res_is_nan || res_is_inf) ? 11'h7FF :
                             (res_is_zero)              ? 11'h000 :
                             (res_exp + 13'd1023);

    wire [63:0] fp_out_wire;
    // 假设 fp_recomposer 存在
    fp_recomposer u_rec (
        .final_sign(res_sign),
        .final_exponent_field(final_exp_field),
        .final_mantissa_field(res_man[51:0]), // 取低52位小数部分
        .is_nan_out(res_is_nan),
        .is_inf_out(res_is_inf),
        .is_zero_out(res_is_zero),
        .fp_out(fp_out_wire)
    );
    
    always @(posedge clk) begin
        if (state == S_DONE) begin
            fp_out <= fp_out_wire;
        end
    end

endmodule
`default_nettype wire

tb/tb_fp_div.v
`timescale 1ns / 1ps

module tb_fp_div;

    // 1. 信号定义
    reg         tb_clk;
    reg         tb_rst_n;      // 注意：设计中使用的是低电平复位 rst_n
    reg         tb_start;      // 开始信号
    reg  [63:0] tb_fp_a;       // 被除数
    reg  [63:0] tb_fp_b;       // 除数
    
    wire [63:0] tb_fp_out;     // 结果输出
    wire        tb_done;       // 完成信号
    wire        tb_overflow;   // 标志位监测
    wire        tb_underflow;
    wire        tb_invalid;

    // 2. 实例化待测模块 (DUT)
    fp_div uut (
        .clk        (tb_clk),
        .rst_n      (tb_rst_n),
        .start      (tb_start),
        .fp_a       (tb_fp_a),
        .fp_b       (tb_fp_b),
        .fp_out     (tb_fp_out),
        .done       (tb_done),
        .overflow   (tb_overflow),
        .underflow  (tb_underflow),
        .invalid    (tb_invalid)
    );

    // 3. 时钟生成 (10ns 周期 -> 100MHz)
    always #5 tb_clk = ~tb_clk;

    // 4. 定义测试任务
    task run_test;
        input [63:0] a;
        input [63:0] b;
        input [63:0] expected;
        input [511:0] test_name; // 增加字符串长度以防截断
        
        reg [31:0] timeout_counter;
        begin
            @(posedge tb_clk);
            tb_fp_a = a;
            tb_fp_b = b;
            tb_start = 1; // 发送 Start 脉冲
            @(posedge tb_clk);
            tb_start = 0;
            
            // 等待 done 信号
            timeout_counter = 0;
            while (!tb_done && timeout_counter < 200) begin
                @(posedge tb_clk);
                timeout_counter = timeout_counter + 1;
            end

            // 结果检查
            if (timeout_counter >= 200) begin
                $display("ERROR: %0s. Test timed out!", test_name);
            end else begin
                // 使用 === 进行严格比对 (包括 x/z，尽管这里预期是确定的值)
                // 注意：对于 NaN，FP标准中 NaN != NaN，但在硬件仿真中我们比对位模式
                if (tb_fp_out === expected) begin
                    $display("PASS: %-45s. Got=%h (Flags: Ov=%b Un=%b Inv=%b)", 
                             test_name, tb_fp_out, tb_overflow, tb_underflow, tb_invalid);
                end else begin
                    $display("FAIL: %-45s. Expected=%h, Got=%h", test_name, expected, tb_fp_out);
                end
            end
            
            // 插入一点间隙
            repeat(2) @(posedge tb_clk);
        end
    endtask

    // 5. 测试主流程
    initial begin
        // 初始化
        tb_clk = 0;
        tb_rst_n = 0; // 复位有效
        tb_start = 0;
        tb_fp_a = 0;
        tb_fp_b = 0;

        // 生成波形文件 (可选)
        $dumpfile("tb_fp_div.vcd");
        $dumpvars(0, tb_fp_div);

        // 释放复位
        #20;
        @(posedge tb_clk);
        tb_rst_n = 1;
        @(posedge tb_clk);
        
        $display("================== 开始测试 fp_div_64 ==================");

        // --- 基础运算 ---
        // 6.0 / 2.0 = 3.0
        run_test(64'h4018000000000000, 64'h4000000000000000, 64'h4008000000000000, 
                 "Test 1: 6.0 / 2.0 (Basic)"); 
                 
        // -6.0 / 2.0 = -3.0 (符号位测试)
        run_test(64'hC018000000000000, 64'h4000000000000000, 64'hC008000000000000, 
                 "Test 2: -6.0 / 2.0 (Sign Mix)");
                 
        // 1.0 / 1.0 = 1.0 (单位测试)
        run_test(64'h3FF0000000000000, 64'h3FF0000000000000, 64'h3FF0000000000000, 
                 "Test 3: 1.0 / 1.0 (Identity)"); 

        // --- 精度与舍入 ---
        // 1.0 / 3.0 = 0.3333... (测试 Guard/Round/Sticky 逻辑)
        // 预期结果：3FD5555555555555
        run_test(64'h3FF0000000000000, 64'h4008000000000000, 64'h3FD5555555555555, 
                 "Test 4: 1.0 / 3.0 (Rounding check)");

        // 1.0 / 10.0 = 0.1 (常见循环小数)
        // 1.0: 3FF0000000000000, 10.0: 4024000000000000
        // 0.1: 3FB999999999999A (Round to Nearest Even, clear distinct pattern)
        run_test(64'h3FF0000000000000, 64'h4024000000000000, 64'h3FB999999999999A, 
                 "Test 5: 1.0 / 10.0 (Precision)");

        // --- 特殊值处理 (Exceptions) ---
        
        // 5.0 / 0.0 = +Inf (除零异常)
        // Inf Hex: 7FF0000000000000
        run_test(64'h4014000000000000, 64'h0000000000000000, 64'h7FF0000000000000, 
                 "Test 6: 5.0 / 0.0 (Div by Zero -> Inf)");  
        
        // 0.0 / 5.0 = 0.0 (被除数为0)
        run_test(64'h0000000000000000, 64'h4014000000000000, 64'h0000000000000000, 
                 "Test 7: 0.0 / 5.0 (Zero Numerator)"); 

        // 0.0 / 0.0 = NaN (非法操作)
        // 本设计中 NaN 定义为: 7FF8000000000001
        run_test(64'h0000000000000000, 64'h0000000000000000, 64'h7FF8000000000001, 
                 "Test 8: 0.0 / 0.0 (Invalid -> NaN)"); 
        
        // 5.0 / Inf = 0.0
        run_test(64'h4014000000000000, 64'h7FF0000000000000, 64'h0000000000000000, 
                 "Test 9: 5.0 / Inf (Div by Inf -> 0)"); 
        
        // Inf / Inf = NaN
        run_test(64'h7FF0000000000000, 64'h7FF0000000000000, 64'h7FF8000000000001, 
                 "Test 10: Inf / Inf (Invalid -> NaN)");  
        
        // NaN / 5.0 = NaN (NaN 传播)
        run_test(64'h7FF8000000000001, 64'h4014000000000000, 64'h7FF8000000000001, 
                 "Test 11: NaN / 5.0 (NaN Propagation)"); 

        // --- 边界情况：下溢 (Flush to Zero) ---
        // 最小规格化数 / 2^100 
        // A = 2^-1022 (Min Normal) = 0010000000000000
        // B = 2^100  = 4630000000000000
        // Res 应该下溢为 0
        run_test(64'h0010000000000000, 64'h4630000000000000, 64'h0000000000000000, 
                 "Test 12: Min_Norm / Large (Underflow -> 0)");

        $display("================== 结束测试 fp_div_64 ==================");
        #20;
        $finish;
    end

endmodule

vcd/tb_fp_div.vcd
$date
	Sat Dec 27 18:39:51 2025
$end
$version
	Icarus Verilog
$end
$timescale
	1ps
$end
$scope module tb_fp_div $end
$var wire 1 ! tb_underflow $end
$var wire 1 " tb_overflow $end
$var wire 1 # tb_invalid $end
$var wire 64 $ tb_fp_out [63:0] $end
$var wire 1 % tb_done $end
$var reg 1 & tb_clk $end
$var reg 64 ' tb_fp_a [63:0] $end
$var reg 64 ( tb_fp_b [63:0] $end
$var reg 1 ) tb_rst_n $end
$var reg 1 * tb_start $end
$scope module uut $end
$var wire 1 + calc_sign $end
$var wire 1 , check_inf $end
$var wire 1 - check_nan $end
$var wire 1 . check_zero $end
$var wire 1 & clk $end
$var wire 64 / fp_a [63:0] $end
$var wire 64 0 fp_b [63:0] $end
$var wire 1 1 is_invalid_op $end
$var wire 1 2 rounder_s $end
$var wire 1 ) rst_n $end
$var wire 1 * start $end
$var wire 1 3 sign_b $end
$var wire 1 4 sign_a $end
$var wire 1 5 rounder_r $end
$var wire 53 6 rounder_mant_out [52:0] $end
$var wire 53 7 rounder_mant_in [52:0] $end
$var wire 1 8 rounder_g $end
$var wire 1 9 rounder_carry $end
$var wire 53 : man_b [52:0] $end
$var wire 53 ; man_a [52:0] $end
$var wire 1 < is_zero_b $end
$var wire 1 = is_zero_a $end
$var wire 1 > is_nan_b $end
$var wire 1 ? is_nan_a $end
$var wire 1 @ is_inf_b $end
$var wire 1 A is_inf_a $end
$var wire 1 B is_denorm_b $end
$var wire 1 C is_denorm_a $end
$var wire 64 D fp_out_wire [63:0] $end
$var wire 11 E final_exp_field [10:0] $end
$var wire 12 F exp_b [11:0] $end
$var wire 12 G exp_a [11:0] $end
$var parameter 3 H S_DIVIDE $end
$var parameter 3 I S_DONE $end
$var parameter 3 J S_IDLE $end
$var parameter 3 K S_NORMALIZE $end
$var parameter 3 L S_PACK $end
$var parameter 3 M S_PREPARE $end
$var parameter 3 N S_ROUND $end
$var reg 6 O div_cnt [5:0] $end
$var reg 54 P divisor_core [53:0] $end
$var reg 1 % done $end
$var reg 64 Q fp_out [63:0] $end
$var reg 1 # invalid $end
$var reg 1 " overflow $end
$var reg 56 R quotient_reg [55:0] $end
$var reg 110 S remainder_reg [109:0] $end
$var reg 14 T res_exp [13:0] $end
$var reg 1 U res_is_inf $end
$var reg 1 V res_is_nan $end
$var reg 1 W res_is_zero $end
$var reg 53 X res_man [52:0] $end
$var reg 1 Y res_sign $end
$var reg 3 Z state [2:0] $end
$var reg 1 ! underflow $end
$scope module u_dec_a $end
$var wire 64 [ fp_in [63:0] $end
$var wire 1 C is_denormalized $end
$var wire 1 A is_inf $end
$var wire 1 ? is_nan $end
$var wire 1 \ is_special_exp $end
$var wire 1 = is_zero $end
$var wire 1 4 sign $end
$var wire 1 ] raw_sign $end
$var wire 52 ^ raw_mantissa [51:0] $end
$var wire 11 _ raw_exponent [10:0] $end
$var wire 53 ` mantissa [52:0] $end
$var wire 1 a is_mantissa_zero $end
$var wire 12 b exponent [11:0] $end
$var parameter 11 c EXP_ALL_ONES $end
$var parameter 11 d EXP_ALL_ZEROS $end
$var parameter 13 e EXP_BIAS $end
$upscope $end
$scope module u_dec_b $end
$var wire 64 f fp_in [63:0] $end
$var wire 1 B is_denormalized $end
$var wire 1 @ is_inf $end
$var wire 1 > is_nan $end
$var wire 1 g is_special_exp $end
$var wire 1 < is_zero $end
$var wire 1 3 sign $end
$var wire 1 h raw_sign $end
$var wire 52 i raw_mantissa [51:0] $end
$var wire 11 j raw_exponent [10:0] $end
$var wire 53 k mantissa [52:0] $end
$var wire 1 l is_mantissa_zero $end
$var wire 12 m exponent [11:0] $end
$var parameter 11 n EXP_ALL_ONES $end
$var parameter 11 o EXP_ALL_ZEROS $end
$var parameter 13 p EXP_BIAS $end
$upscope $end
$scope module u_rec $end
$var wire 11 q final_exponent_field [10:0] $end
$var wire 52 r final_mantissa_field [51:0] $end
$var wire 1 Y final_sign $end
$var wire 1 U is_inf_out $end
$var wire 1 V is_nan_out $end
$var wire 1 W is_zero_out $end
$var wire 64 s fp_out [63:0] $end
$upscope $end
$scope module u_rounder $end
$var wire 1 8 g $end
$var wire 53 t mant_in [52:0] $end
$var wire 1 5 r $end
$var wire 1 u round_decision $end
$var wire 1 2 s $end
$var wire 54 v rounded_result [53:0] $end
$var wire 53 w mant_out [52:0] $end
$var wire 1 x lsb $end
$var wire 1 9 carry_out $end
$upscope $end
$upscope $end
$scope task run_test $end
$var reg 64 y a [63:0] $end
$var reg 64 z b [63:0] $end
$var reg 64 { expected [63:0] $end
$var reg 512 | test_name [511:0] $end
$var reg 32 } timeout_counter [31:0] $end
$upscope $end
$upscope $end
$enddefinitions $end
$comment Show the parameter values. $end
$dumpall
b1111111111 p
b0 o
b11111111111 n
b1111111111 e
b0 d
b11111111111 c
b100 N
b1 M
b101 L
b11 K
b0 J
b110 I
b10 H
$end
#0
$dumpvars
bx }
bx |
bx {
bx z
bx y
0x
b0 w
b0 v
0u
b0 t
b11111111110000000000000000000000000000000000000000000000000000 s
b0 r
b1111111111 q
b0 m
1l
b0 k
b0 j
b0 i
0h
1g
b0 f
b0 b
1a
b0 `
b0 _
b0 ^
0]
1\
b0 [
b0 Z
0Y
b0 X
0W
0V
0U
b0 T
b0 S
b0 R
b0 Q
b0 P
b0 O
b0 G
b0 F
b1111111111 E
b11111111110000000000000000000000000000000000000000000000000000 D
0C
0B
0A
0@
0?
0>
1=
1<
b0 ;
b0 :
09
08
b0 7
b0 6
05
04
03
02
11
b0 0
b0 /
0.
1-
0,
0+
0*
0)
b0 (
b0 '
0&
0%
b0 $
0#
0"
0!
$end
#5000
1&
#10000
0&
#15000
1&
#20000
0&
#25000
1)
1&
#30000
0&
#35000
b1010100011001010111001101110100001000000011000100111010001000000011011000101110001100000010000000101111001000000011001000101110001100000010000000101000010000100110000101110011011010010110001100101001 |
b100000000001000000000000000000000000000000000000000000000000000 {
b100000000000000000000000000000000000000000000000000000000000000 z
b100000000011000000000000000000000000000000000000000000000000000 y
1&
#40000
0&
#45000
b1 Z
b1 F
b1 m
b10 G
b10 b
0-
b10000000000000000000000000000000000000000000000000000 :
b10000000000000000000000000000000000000000000000000000 k
b11000000000000000000000000000000000000000000000000000 ;
b11000000000000000000000000000000000000000000000000000 `
01
0g
0<
0\
0=
b10000000000 j
b10000000001 _
0a
b1000000000000000000000000000000000000000000000000000 ^
1*
b100000000000000000000000000000000000000000000000000000000000000 (
b100000000000000000000000000000000000000000000000000000000000000 0
b100000000000000000000000000000000000000000000000000000000000000 f
b100000000011000000000000000000000000000000000000000000000000000 '
b100000000011000000000000000000000000000000000000000000000000000 /
b100000000011000000000000000000000000000000000000000000000000000 [
1&
#50000
0&
#55000
b100000000000000000000000000000000000000000000000000000000000000 D
b100000000000000000000000000000000000000000000000000000000000000 s
b10000000000 E
b10000000000 q
12
b10 Z
b111000 O
b10000000000000000000000000000000000000000000000000000 P
b1100000000000000000000000000000000000000000000000000000000000000000000000000000000000000000000000000000000000 S
b1 T
b0 }
0*
1&
#60000
0&
#65000
b110111 O
b1 R
b1000000000000000000000000000000000000000000000000000000000000000000000000000000000000000000000000000000000000 S
b1 }
1&
#70000
0&
#75000
15
b110110 O
b11 R
b0 S
b10 }
1&
#80000
0&
#85000
b1 6
b1 w
b1 v
1u
02
18
b110101 O
b110 R
b11 }
1&
#90000
0&
#95000
1x
b10 6
b10 w
b10 v
b1 7
b1 t
05
b110100 O
b1100 R
b100 }
1&
#100000
0&
#105000
b11 6
b11 w
0u
b11 v
b11 7
b11 t
08
b110011 O
b11000 R
b101 }
1&
#110000
0&
#115000
0x
b110 6
b110 w
b110 v
b110 7
b110 t
b110010 O
b110000 R
b110 }
1&
#120000
0&
#125000
b1100 6
b1100 w
b1100 v
b1100 7
b1100 t
b110001 O
b1100000 R
b111 }
1&
#130000
0&
#135000
b11000 6
b11000 w
b11000 v
b11000 7
b11000 t
b110000 O
b11000000 R
b1000 }
1&
#140000
0&
#145000
b110000 6
b110000 w
b110000 v
b110000 7
b110000 t
b101111 O
b110000000 R
b1001 }
1&
#150000
0&
#155000
b1100000 6
b1100000 w
b1100000 v
b1100000 7
b1100000 t
b101110 O
b1100000000 R
b1010 }
1&
#160000
0&
#165000
b11000000 6
b11000000 w
b11000000 v
b11000000 7
b11000000 t
b101101 O
b11000000000 R
b1011 }
1&
#170000
0&
#175000
b110000000 6
b110000000 w
b110000000 v
b110000000 7
b110000000 t
b101100 O
b110000000000 R
b1100 }
1&
#180000
0&
#185000
b1100000000 6
b1100000000 w
b1100000000 v
b1100000000 7
b1100000000 t
b101011 O
b1100000000000 R
b1101 }
1&
#190000
0&
#195000
b11000000000 6
b11000000000 w
b11000000000 v
b11000000000 7
b11000000000 t
b101010 O
b11000000000000 R
b1110 }
1&
#200000
0&
#205000
b110000000000 6
b110000000000 w
b110000000000 v
b110000000000 7
b110000000000 t
b101001 O
b110000000000000 R
b1111 }
1&
#210000
0&
#215000
b1100000000000 6
b1100000000000 w
b1100000000000 v
b1100000000000 7
b1100000000000 t
b101000 O
b1100000000000000 R
b10000 }
1&
#220000
0&
#225000
b11000000000000 6
b11000000000000 w
b11000000000000 v
b11000000000000 7
b11000000000000 t
b100111 O
b11000000000000000 R
b10001 }
1&
#230000
0&
#235000
b110000000000000 6
b110000000000000 w
b110000000000000 v
b110000000000000 7
b110000000000000 t
b100110 O
b110000000000000000 R
b10010 }
1&
#240000
0&
#245000
b1100000000000000 6
b1100000000000000 w
b1100000000000000 v
b1100000000000000 7
b1100000000000000 t
b100101 O
b1100000000000000000 R
b10011 }
1&
#250000
0&
#255000
b11000000000000000 6
b11000000000000000 w
b11000000000000000 v
b11000000000000000 7
b11000000000000000 t
b100100 O
b11000000000000000000 R
b10100 }
1&
#260000
0&
#265000
b110000000000000000 6
b110000000000000000 w
b110000000000000000 v
b110000000000000000 7
b110000000000000000 t
b100011 O
b110000000000000000000 R
b10101 }
1&
#270000
0&
#275000
b1100000000000000000 6
b1100000000000000000 w
b1100000000000000000 v
b1100000000000000000 7
b1100000000000000000 t
b100010 O
b1100000000000000000000 R
b10110 }
1&
#280000
0&
#285000
b11000000000000000000 6
b11000000000000000000 w
b11000000000000000000 v
b11000000000000000000 7
b11000000000000000000 t
b100001 O
b11000000000000000000000 R
b10111 }
1&
#290000
0&
#295000
b110000000000000000000 6
b110000000000000000000 w
b110000000000000000000 v
b110000000000000000000 7
b110000000000000000000 t
b100000 O
b110000000000000000000000 R
b11000 }
1&
#300000
0&
#305000
b1100000000000000000000 6
b1100000000000000000000 w
b1100000000000000000000 v
b1100000000000000000000 7
b1100000000000000000000 t
b11111 O
b1100000000000000000000000 R
b11001 }
1&
#310000
0&
#315000
b11000000000000000000000 6
b11000000000000000000000 w
b11000000000000000000000 v
b11000000000000000000000 7
b11000000000000000000000 t
b11110 O
b11000000000000000000000000 R
b11010 }
1&
#320000
0&
#325000
b110000000000000000000000 6
b110000000000000000000000 w
b110000000000000000000000 v
b110000000000000000000000 7
b110000000000000000000000 t
b11101 O
b110000000000000000000000000 R
b11011 }
1&
#330000
0&
#335000
b1100000000000000000000000 6
b1100000000000000000000000 w
b1100000000000000000000000 v
b1100000000000000000000000 7
b1100000000000000000000000 t
b11100 O
b1100000000000000000000000000 R
b11100 }
1&
#340000
0&
#345000
b11000000000000000000000000 6
b11000000000000000000000000 w
b11000000000000000000000000 v
b11000000000000000000000000 7
b11000000000000000000000000 t
b11011 O
b11000000000000000000000000000 R
b11101 }
1&
#350000
0&
#355000
b110000000000000000000000000 6
b110000000000000000000000000 w
b110000000000000000000000000 v
b110000000000000000000000000 7
b110000000000000000000000000 t
b11010 O
b110000000000000000000000000000 R
b11110 }
1&
#360000
0&
#365000
b1100000000000000000000000000 6
b1100000000000000000000000000 w
b1100000000000000000000000000 v
b1100000000000000000000000000 7
b1100000000000000000000000000 t
b11001 O
b1100000000000000000000000000000 R
b11111 }
1&
#370000
0&
#375000
b11000000000000000000000000000 6
b11000000000000000000000000000 w
b11000000000000000000000000000 v
b11000000000000000000000000000 7
b11000000000000000000000000000 t
b11000 O
b11000000000000000000000000000000 R
b100000 }
1&
#380000
0&
