src/common/fp_rounder.v
// src/common/fp_rounder.v
// 功能：根据G, R, S位实现平衡型舍入(Round to Nearest, Ties to Even)

`default_nettype none

module fp_rounder (
    input  wire [52:0] mant_in,      // 输入的53位尾数 (规格化后的)
    input  wire        g,            // Guard bit
    input  wire        r,            // Round bit
    input  wire        s,            // Sticky bit

    output wire [52:0] mant_out,     // 舍入后的53位尾数
    output wire        carry_out     // 舍入后产生的进位 (例如 1.11...1 + 1 -> 10.00...0)
);

    wire round_decision;
    wire lsb = mant_in[0]; // 待舍入的尾数的最低位

    // 平衡型舍入决策逻辑
    // 当丢弃部分 > 0.5 LSB 时，或
    // 当丢弃部分 = 0.5 LSB 且尾数最低位为1时，向上舍入
    assign round_decision = g & (r | s | lsb);

    // 执行舍入操作：将决策位加到尾数上
    // 使用54位加法器以捕获可能的进位
    wire [53:0] rounded_result;
    assign rounded_result = {1'b0, mant_in} + round_decision;

    // 输出结果
    assign mant_out = rounded_result[52:0];
    assign carry_out = rounded_result[53];

endmodule

`default_nettype wire

src/common/fp_decomposer.v
// src/common/fp_decomposer.v
// 功能：将64位双精度浮点数分解为符号、指数、尾数及特殊标志位

`default_nettype none

module fp_decomposer (
    input  wire [63:0] fp_in,          // 输入的64位浮点数

    output wire        sign,           // 符号位
    output wire signed [11:0] exponent,       // 12位指数 (含符号，为方便计算)
    output wire [52:0] mantissa,       // 53位尾数 (规格化数含隐藏位'1', 非规格化数含'0')
    
    output wire        is_nan,         // 是不是NaN
    output wire        is_inf,         // 是不是无穷大
    output wire        is_zero,        // 是不是零
    output wire        is_denormalized // 是不是非规格化数
);

    // 1. 直接从输入中拆分字段
    wire        raw_sign      = fp_in[63];
    wire [10:0] raw_exponent  = fp_in[62:52];
    wire [51:0] raw_mantissa  = fp_in[51:0];

    // 2. 定义特殊指数值
    localparam EXP_ALL_ZEROS = 11'h000;
    localparam EXP_ALL_ONES  = 11'h7FF;
    localparam EXP_BIAS      = 1023;

    // 3. 判断特殊类型
    wire is_special_exp = (raw_exponent == EXP_ALL_ZEROS) || (raw_exponent == EXP_ALL_ONES);
    wire is_mantissa_zero = (raw_mantissa == 52'h0);

    // is_nan: exp全1, mantissa非0. [3, 4]
    assign is_nan = (raw_exponent == EXP_ALL_ONES) && (!is_mantissa_zero);
    
    // is_inf: exp全1, mantissa为0. [3, 4]
    assign is_inf = (raw_exponent == EXP_ALL_ONES) && (is_mantissa_zero);
    
    // is_zero: exp全0, mantissa为0. [4]
    assign is_zero = (raw_exponent == EXP_ALL_ZEROS) && (is_mantissa_zero);
    
    // is_denormalized: exp全0, mantissa非0. [4]
    assign is_denormalized = (raw_exponent == EXP_ALL_ZEROS) && (!is_mantissa_zero);

    // 4. 计算输出
    assign sign = raw_sign;

    // 指数计算：
    // - 规格化数: 实际指数 = 偏移指数 - 偏移量
    // - 非规格化数: 实际指数固定为 1 - 偏移量 = -1022
    // - 特殊值: 指数可以设为0，因为会被is_nan/is_inf标志处理
    assign exponent = (is_denormalized)   ? (1 - EXP_BIAS) :          // 非规格化数，指数为 1-1023 = -1022
                    (is_special_exp)   ? 12'd0 :                   // 特殊值 (Inf, NaN)，指数可为0
                                     (raw_exponent - EXP_BIAS);  // 规格化数


    // 尾数计算：
    // - 规格化数: 尾数 = {1'b1, raw_mantissa}
    // - 非规格化数: 尾数 = {1'b0, raw_mantissa}
    // - 特殊值(0, inf, nan): 尾数可以为0，由标志位处理
    assign mantissa = (is_denormalized) ? {1'b0, raw_mantissa} : 
                      (is_special_exp) ? 53'd0 : 
                                         {1'b1, raw_mantissa};            
endmodule

`default_nettype wire

src/fp_to_int.v
`default_nettype none

module fp_to_int (
    input  wire [63:0] fp_in,
    output reg  [63:0] int_out
);

    // =========================================================================
    // 1. 浮点数分解
    // =========================================================================
    wire        sign;
    wire signed [11:0] exponent;
    wire [52:0] mantissa;
    wire        is_nan;
    wire        is_inf;
    // is_zero, is_denormalized 此处不直接使用，逻辑中已覆盖

    fp_decomposer u_decomposer (
        .fp_in           (fp_in),
        .sign            (sign),
        .exponent        (exponent),
        .mantissa        (mantissa),
        .is_nan          (is_nan),
        .is_inf          (is_inf),
        .is_zero         (), 
        .is_denormalized () 
    );

    // =========================================================================
    // 2. 预处理：准备舍入所需的 G, R, S 位
    // =========================================================================
    
    // 只有当 exponent <= 52 时，才涉及到小数部分的舍入。
    // 如果 exponent > 52，尾数完全位于整数部分，无小数，G=R=S=0。
    
    // 我们构建一个宽的移位寄存器来提取整数部分和小数位。
    // 构造 {mantissa, 64'b0} (共117位)，相当于左对齐。
    // 右移量 = 52 - exponent。
    // 例如：exp=52 -> shift=0,  mantissa全为整数。
    //       exp=0  -> shift=52, mantissa[52]为整数LSB, 其余为小数。
    
    reg [6:0]   r_shift_amt;
    reg [116:0] shifted_mant;
    
    always @(*) begin
        if (exponent <= 52 && exponent >= -60) begin 
            // 正常的转换范围，或者非常小的数（全小数）
            // 注意：exponent 是有符号的，需要处理负数情况
            r_shift_amt = 7'd52 - exponent[6:0]; 
        end else if (exponent < -60) begin
            // 极小的数，完全移出，全为 Sticky
            r_shift_amt = 7'd116; 
        end else begin
            // Exponent > 52，此路径不使用移位逻辑生成小数
            r_shift_amt = 7'd0;
        end
        
        shifted_mant = {mantissa, 64'b0} >> r_shift_amt;
    end

    // 提取送入 Rounder 的信号
    // 整数部分 (送入 mant_in): 位于 shifted_mant 的高 53 位 [116:64]
    // Guard bit (0.5权重):      位于 bit 63
    // Round bit (0.25权重):     位于 bit 62
    // Sticky bit (剩余所有):    位于 bit [61:0] 的 OR
    
    wire [52:0] rounder_mant_in = shifted_mant[116:64];
    wire        rounder_g       = shifted_mant[63];
    wire        rounder_r       = shifted_mant[62];
    wire        rounder_s       = |shifted_mant[61:0];

    // =========================================================================
    // 3. 实例化舍入模块 (fp_rounder)
    // =========================================================================
    wire [52:0] rounder_mant_out;
    wire        rounder_carry;

    // 这里复用 fp_rounder。虽然它是为浮点尾数设计的，但其逻辑:
    // "若满足舍入条件则加1" 对整数转换同样适用。
    fp_rounder u_rounder (
        .mant_in     (rounder_mant_in),
        .g           (rounder_g),
        .r           (rounder_r),
        .s           (rounder_s),
        .mant_out    (rounder_mant_out),
        .carry_out   (rounder_carry)
    );

    // 组合舍入后的绝对值 (针对 Exp <= 52 的情况)
    // 结果 = {进位, 舍入后的53位}
    wire [53:0] abs_int_small = {rounder_carry, rounder_mant_out};

    // =========================================================================
    // 4. 大数处理 (Exp > 52) 与 结果选择
    // =========================================================================
    
    // int64 最大正整数 2^63 - 1。
    // 如果 exp > 52，我们需要左移还原整数。
    // 这里的 shift 是 exponent - 52。
    
    reg [63:0] abs_int_large;
    always @(*) begin
        // 限制左移位宽防止仿真报错，实际溢出会由后续逻辑处理
        if (exponent > 52 && exponent < 116) begin
            abs_int_large = {11'b0, mantissa} << (exponent - 52);
        end else begin
            // 极大溢出，设为全1方便后续饱和处理
            abs_int_large = 64'hFFFF_FFFF_FFFF_FFFF; 
        end
    end

    // 综合绝对值
    reg [63:0] abs_result;
    always @(*) begin
        if (exponent > 52) begin
            abs_result = abs_int_large;
        end else begin
            // 高位补0
            abs_result = {10'b0, abs_int_small}; 
        end
    end

    // =========================================================================
    // 5. 符号处理与溢出饱和 (Saturation)
    // =========================================================================
    
    localparam [63:0] MAX_INT = 64'h7FFF_FFFF_FFFF_FFFF; //  9223372036854775807
    localparam [63:0] MIN_INT = 64'h8000_0000_0000_0000; // -9223372036854775808

    always @(*) begin
        if (is_nan) begin
            int_out = 64'd0;
        end
        else if (is_inf) begin
            int_out = sign ? MIN_INT : MAX_INT;
        end
        else begin
            // 检查溢出
            // 1. Exp >= 63: 肯定溢出 (除了 -2^63 这个特例)
            // 2. Exp < 63: 需要检查计算出的 abs_result 是否越界
            
            if (exponent >= 63) begin
                // 特例: -2^63 (exp=63, mant=1.0)
                // 注意 mantissa 包含隐藏位，如果是 1.0...0，mantissa 值为 53'h10_0000...
                // 但这里 mantissa 信号来自 decomposer，如果是规格化数，它是 {1, raw}
                // 精确的 2^63 浮点数: Exponent 63, Mantissa 1.0
                if (sign && exponent == 63 && mantissa == 53'h10_0000_0000_0000) begin
                    int_out = MIN_INT; // 合法
                end else begin
                    int_out = sign ? MIN_INT : MAX_INT; // 饱和
                end
            end
            else begin
                // Exponent <= 62
                // 此时 abs_result 最大可能为 2^63 (如果 Exp=62 且发生进位，或者 Exp=62 Mantissa大)
                // 检查位 63
                if (abs_result[63]) begin
                    // 绝对值 >= 2^63
                    // 只有 -2^63 是合法的
                    if (sign && abs_result == MIN_INT) begin // abs_result == 2^63 (as unsigned 0x8000...)
                        int_out = MIN_INT;
                    end else begin
                        // 正数溢出 或 负数超过 -2^63
                        int_out = sign ? MIN_INT : MAX_INT;
                    end
                end 
                else begin
                    // 正常范围
                    int_out = sign ? -abs_result : abs_result;
                end
            end
        end
    end

endmodule
`default_nettype wire

tb/tb_fp_to_int.v
`timescale 1ns / 1ps

module tb_fp_to_int;

    // 1. 信号定义
    reg  [63:0] tb_fp_in;      // 输入：双精度浮点数
    wire [63:0] tb_int_out;    // 输出：64位整形 (Signed Long)

    // 2. 实例化待测模块 (DUT)
    fp_to_int uut (
        .fp_in      (tb_fp_in),
        .int_out    (tb_int_out)
    );

    // 3. 定义测试任务
    // 类似于参考代码中的 run_test，但针对组合逻辑进行了简化
    task run_test;
        input [63:0] fp_val;        // 输入浮点数
        input [63:0] expected_int;  // 预期整形值
        input [511:0] test_name;    // 测试名称
        
        begin
            // 赋值输入
            tb_fp_in = fp_val;
            
            // 等待组合逻辑稳定 (模拟传播延迟)
            #10; 

            // 结果检查
            if (tb_int_out === expected_int) begin
                $display("PASS: %-45s. In=%h, Got=%h (Dec:%0d)", 
                         test_name, fp_val, tb_int_out, $signed(tb_int_out));
            end else begin
                $display("FAIL: %-45s. Expected=%h, Got=%h", test_name, expected_int, tb_int_out);
                $display("      Expected Dec: %0d, Got Dec: %0d", $signed(expected_int), $signed(tb_int_out));
            end
            
            // 插入间隙
            #10;
        end
    endtask

    // 4. 测试主流程
    initial begin
        // 初始化
        tb_fp_in = 0;

        // 生成波形文件 (可选)
        $dumpfile("tb_fp_to_int.vcd");
        $dumpvars(0, tb_fp_to_int);

        $display("================== 开始测试 fp_to_int (Round to Nearest Even) ==================");
        #10;

        // --- 1. 基础整数转换 ---
        // 1.0 -> 1
        run_test(64'h3FF0000000000000, 64'h0000000000000001, 
                 "Test 1: 1.0 -> 1");
        
        // -1.0 -> -1
        run_test(64'hBFF0000000000000, 64'hFFFFFFFFFFFFFFFF, 
                 "Test 2: -1.0 -> -1");

        // 0.0 -> 0
        run_test(64'h0000000000000000, 64'h0000000000000000, 
                 "Test 3: 0.0 -> 0");

        // --- 2. 正常舍入测试 (普通四舍五入) ---
        // 1.2 -> 1 (舍去)
        // Hex: 3FF3333333333333
        run_test(64'h3FF3333333333333, 64'h0000000000000001, 
                 "Test 4: 1.2 -> 1 (Round Down)");

        // 1.8 -> 2 (进位)
        // Hex: 3FFCCCCCCCCCCCCD
        run_test(64'h3FFCCCCCCCCCCCCD, 64'h0000000000000002, 
                 "Test 5: 1.8 -> 2 (Round Up)");

        // --- 3. 平衡舍入/银行家舍入 (Round to Nearest Even) ---
        // 规则：x.5 时，向最近的偶数舍入
        
        // 2.5 -> 2 (舍去，因为2是偶数)
        // Hex: 4004000000000000
        run_test(64'h4004000000000000, 64'h0000000000000002, 
                 "Test 6: 2.5 -> 2 (Tie-break to Even Down)");

        // 1.5 -> 2 (进位，因为2是偶数)
        // Hex: 3FF8000000000000
        run_test(64'h3FF8000000000000, 64'h0000000000000002, 
                 "Test 7: 1.5 -> 2 (Tie-break to Even Up)");
        
        // 3.5 -> 4 (进位，因为4是偶数)
        // Hex: 400C000000000000
        run_test(64'h400C000000000000, 64'h0000000000000004, 
                 "Test 8: 3.5 -> 4 (Tie-break to Even Up)");

        // -2.5 -> -2 (舍去，因为-2是偶数)
        // Hex: C004000000000000 -> Int: FFFFFFFFFFFFFFFE
        run_test(64'hC004000000000000, 64'hFFFFFFFFFFFFFFFE, 
                 "Test 9: -2.5 -> -2 (Negative Tie-break)");

        // --- 4. 边界与大数测试 ---
        
        // 小数测试：0.4 -> 0
        // Hex: 3FD999999999999A
        run_test(64'h3FD999999999999A, 64'h0000000000000000, 
                 "Test 10: 0.4 -> 0 (Small Number)");

        // 大数测试：2^60
        // 2^60 FP: 43B0000000000000
        // 2^60 Int: 1000000000000000
        run_test(64'h43B0000000000000, 64'h1000000000000000, 
                 "Test 11: 2^60 (Large Number)");

        // 负大数测试：-2^60
        // -2^60 FP: C3B0000000000000
        // -2^60 Int: F000000000000000
        run_test(64'hC3B0000000000000, 64'hF000000000000000, 
                 "Test 12: -2^60 (Negative Large Number)");

        // --- 5. 异常值 (可选，视具体实现而定) ---
        // 注意：FP转Int对于 NaN 和 Inf 的标准行为在硬件上通常是定义为
        // 返回整数的最大值或最小值，这里假设 NaN 返回 0 以作演示，实际需根据设计调整。
        // 如果你的设计对 NaN 输出全0：
        // run_test(64'h7FF8000000000001, 64'h0000000000000000, "Test 13: NaN -> 0 (Assumption)");

        $display("================== 结束测试 fp_to_int ==================");
        #20;
        $finish;
    end

endmodule

vcd/tb_fp_to_int.vcd
$date
	Sat Dec 27 18:39:55 2025
$end
$version
	Icarus Verilog
$end
$timescale
	1ps
$end
$scope module tb_fp_to_int $end
$var wire 64 ! tb_int_out [63:0] $end
$var reg 64 " tb_fp_in [63:0] $end
$scope module uut $end
$var wire 64 # fp_in [63:0] $end
$var wire 1 $ sign $end
$var wire 1 % rounder_s $end
$var wire 1 & rounder_r $end
$var wire 53 ' rounder_mant_out [52:0] $end
$var wire 53 ( rounder_mant_in [52:0] $end
$var wire 1 ) rounder_g $end
$var wire 1 * rounder_carry $end
$var wire 53 + mantissa [52:0] $end
$var wire 1 , is_nan $end
$var wire 1 - is_inf $end
$var wire 12 . exponent [11:0] $end
$var wire 54 / abs_int_small [53:0] $end
$var parameter 64 0 MAX_INT $end
$var parameter 64 1 MIN_INT $end
$var reg 64 2 abs_int_large [63:0] $end
$var reg 64 3 abs_result [63:0] $end
$var reg 64 4 int_out [63:0] $end
$var reg 7 5 r_shift_amt [6:0] $end
$var reg 117 6 shifted_mant [116:0] $end
$scope module u_decomposer $end
$var wire 64 7 fp_in [63:0] $end
$var wire 1 8 is_denormalized $end
$var wire 1 - is_inf $end
$var wire 1 , is_nan $end
$var wire 1 9 is_special_exp $end
$var wire 1 : is_zero $end
$var wire 1 $ sign $end
$var wire 1 ; raw_sign $end
$var wire 52 < raw_mantissa [51:0] $end
$var wire 11 = raw_exponent [10:0] $end
$var wire 53 > mantissa [52:0] $end
$var wire 1 ? is_mantissa_zero $end
$var wire 12 @ exponent [11:0] $end
$var parameter 11 A EXP_ALL_ONES $end
$var parameter 11 B EXP_ALL_ZEROS $end
$var parameter 13 C EXP_BIAS $end
$upscope $end
$scope module u_rounder $end
$var wire 1 ) g $end
$var wire 53 D mant_in [52:0] $end
$var wire 1 & r $end
$var wire 1 E round_decision $end
$var wire 1 % s $end
$var wire 54 F rounded_result [53:0] $end
$var wire 53 G mant_out [52:0] $end
$var wire 1 H lsb $end
$var wire 1 * carry_out $end
$upscope $end
$upscope $end
$scope task run_test $end
$var reg 64 I expected_int [63:0] $end
$var reg 64 J fp_val [63:0] $end
$var reg 512 K test_name [511:0] $end
$upscope $end
$upscope $end
$enddefinitions $end
$comment Show the parameter values. $end
$dumpall
b1111111111 C
b0 B
b11111111111 A
b1000000000000000000000000000000000000000000000000000000000000000 1
b111111111111111111111111111111111111111111111111111111111111111 0
$end
#0
$dumpvars
bx K
bx J
bx I
0H
b0 G
b0 F
0E
b0 D
b0 @
1?
b0 >
b0 =
b0 <
0;
1:
19
08
b0 7
b0 6
b110100 5
b0 4
b0 3
b1111111111111111111111111111111111111111111111111111111111111111 2
b0 /
b0 .
0-
0,
b0 +
0*
0)
b0 (
b0 '
0&
0%
0$
b0 #
b0 "
b0 !
$end
#10000
b1 !
b1 4
b1 3
1H
b1 /
b1 '
b1 G
b1 F
b1 (
b1 D
b10000000000000000000000000000000000000000000000000000000000000000 6
b10000000000000000000000000000000000000000000000000000 +
b10000000000000000000000000000000000000000000000000000 >
09
0:
b1111111111 =
b11111111110000000000000000000000000000000000000000000000000000 "
b11111111110000000000000000000000000000000000000000000000000000 #
b11111111110000000000000000000000000000000000000000000000000000 7
b1010100011001010111001101110100001000000011000100111010001000000011000100101110001100000010000000101101001111100010000000110001 K
b1 I
b11111111110000000000000000000000000000000000000000000000000000 J
#30000
b1111111111111111111111111111111111111111111111111111111111111111 !
b1111111111111111111111111111111111111111111111111111111111111111 4
1$
1;
b1011111111110000000000000000000000000000000000000000000000000000 "
b1011111111110000000000000000000000000000000000000000000000000000 #
b1011111111110000000000000000000000000000000000000000000000000000 7
b10101000110010101110011011101000010000000110010001110100010000000101101001100010010111000110000001000000010110100111110001000000010110100110001 K
b1111111111111111111111111111111111111111111111111111111111111111 I
b1011111111110000000000000000000000000000000000000000000000000000 J
#50000
b0 3
0H
b0 /
b0 '
b0 G
b0 F
b0 (
b0 D
b0 6
b110100 5
b0 +
b0 >
b0 .
b0 @
b0 !
b0 4
19
1:
0$
0;
b0 =
b0 "
b0 #
b0 7
b1010100011001010111001101110100001000000011001100111010001000000011000000101110001100000010000000101101001111100010000000110000 K
b0 I
b0 J
#70000
b1 !
b1 4
b1 3
1H
b1 /
b1 '
b1 G
b1 F
b1 (
b1 D
1%
b10011001100110011001100110011001100110011001100110011000000000000 6
b10011001100110011001100110011001100110011001100110011 +
b10011001100110011001100110011001100110011001100110011 >
09
0:
b1111111111 =
0?
b11001100110011001100110011001100110011001100110011 <
b11111111110011001100110011001100110011001100110011001100110011 "
b11111111110011001100110011001100110011001100110011001100110011 #
b11111111110011001100110011001100110011001100110011001100110011 7
b101010001100101011100110111010000100000001101000011101000100000001100010010111000110010001000000010110100111110001000000011000100100000001010000101001001101111011101010110111001100100001000000100010001101111011101110110111000101001 K
b1 I
b11111111110011001100110011001100110011001100110011001100110011 J
#90000
b10 !
b10 4
b10 3
b10 /
b10 '
b10 G
b10 F
1E
1)
1&
b11100110011001100110011001100110011001100110011001101000000000000 6
b11100110011001100110011001100110011001100110011001101 +
b11100110011001100110011001100110011001100110011001101 >
b1100110011001100110011001100110011001100110011001101 <
b11111111111100110011001100110011001100110011001100110011001101 "
b11111111111100110011001100110011001100110011001100110011001101 #
b11111111111100110011001100110011001100110011001100110011001101 7
b10101000110010101110011011101000010000000110101001110100010000000110001001011100011100000100000001011010011111000100000001100100010000000101000010100100110111101110101011011100110010000100000010101010111000000101001 K
b10 I
b11111111111100110011001100110011001100110011001100110011001101 J
#110000
b10 !
b10 4
b10 3
b10 /
b10 '
b10 G
0H
b10 (
b10 D
0&
b10 F
0E
b110011 5
1)
0%
b1 .
b1 @
b101000000000000000000000000000000000000000000000000000000000000000 6
b10100000000000000000000000000000000000000000000000000 +
b10100000000000000000000000000000000000000000000000000 >
b10000000000 =
b100000000000000000000000000000000000000000000000000 <
b100000000000100000000000000000000000000000000000000000000000000 "
b100000000000100000000000000000000000000000000000000000000000000 #
b100000000000100000000000000000000000000000000000000000000000000 7
b101010001100101011100110111010000100000001101100011101000100000001100100010111000110101001000000010110100111110001000000011001000100000001010000101010001101001011001010010110101100010011100100110010101100001011010110010000001110100011011110010000001000101011101100110010101101110001000000100010001101111011101110110111000101001 K
b100000000000100000000000000000000000000000000000000000000000000 J
#130000
b10 !
b10 4
1E
b10 3
1H
b10 /
b10 '
b10 G
b110100 5
b10 F
b1 (
b1 D
1)
b0 .
b0 @
b11000000000000000000000000000000000000000000000000000000000000000 6
b11000000000000000000000000000000000000000000000000000 +
b11000000000000000000000000000000000000000000000000000 >
b1111111111 =
b1000000000000000000000000000000000000000000000000000 <
b11111111111000000000000000000000000000000000000000000000000000 "
b11111111111000000000000000000000000000000000000000000000000000 #
b11111111111000000000000000000000000000000000000000000000000000 7
b10101000110010101110011011101000010000000110111001110100010000000110001001011100011010100100000001011010011111000100000001100100010000000101000010101000110100101100101001011010110001001110010011001010110000101101011001000000111010001101111001000000100010101110110011001010110111000100000010101010111000000101001 K
b11111111111000000000000000000000000000000000000000000000000000 J
#150000
b100 !
b100 4
b100 3
b100 /
b100 '
b100 G
b100 F
b11 (
b11 D
b110011 5
0&
b1 .
b1 @
b111000000000000000000000000000000000000000000000000000000000000000 6
b11100000000000000000000000000000000000000000000000000 +
b11100000000000000000000000000000000000000000000000000 >
b10000000000 =
b1100000000000000000000000000000000000000000000000000 <
b100000000001100000000000000000000000000000000000000000000000000 "
b100000000001100000000000000000000000000000000000000000000000000 #
b100000000001100000000000000000000000000000000000000000000000000 7
b10101000110010101110011011101000010000000111000001110100010000000110011001011100011010100100000001011010011111000100000001101000010000000101000010101000110100101100101001011010110001001110010011001010110000101101011001000000111010001101111001000000100010101110110011001010110111000100000010101010111000000101001 K
b100 I
b100000000001100000000000000000000000000000000000000000000000000 J
#170000
0E
b10 3
0H
b10 /
b10 '
b10 G
b10 F
b10 (
b10 D
b101000000000000000000000000000000000000000000000000000000000000000 6
b10100000000000000000000000000000000000000000000000000 +
b10100000000000000000000000000000000000000000000000000 >
b1111111111111111111111111111111111111111111111111111111111111110 !
b1111111111111111111111111111111111111111111111111111111111111110 4
1$
1;
b100000000000000000000000000000000000000000000000000 <
b1100000000000100000000000000000000000000000000000000000000000000 "
b1100000000000100000000000000000000000000000000000000000000000000 #
b1100000000000100000000000000000000000000000000000000000000000000 7
b10101000110010101110011011101000010000000111001001110100010000000101101001100100010111000110101001000000010110100111110001000000010110100110010001000000010100001001110011001010110011101100001011101000110100101110110011001010010000001010100011010010110010100101101011000100111001001100101011000010110101100101001 K
b1111111111111111111111111111111111111111111111111111111111111110 I
b1100000000000100000000000000000000000000000000000000000000000000 J
#190000
b0 3
1&
0H
b0 /
b0 '
b0 G
b110110 5
b0 F
b0 (
b0 D
0)
1%
b111111111110 .
b111111111110 @
b110011001100110011001100110011001100110011001100110100000000000 6
b11001100110011001100110011001100110011001100110011010 +
b11001100110011001100110011001100110011001100110011010 >
b0 !
b0 4
0$
0;
b1111111101 =
b1001100110011001100110011001100110011001100110011010 <
b11111111011001100110011001100110011001100110011001100110011010 "
b11111111011001100110011001100110011001100110011001100110011010 #
b11111111011001100110011001100110011001100110011001100110011010 7
b101010001100101011100110111010000100000001100010011000000111010001000000011000000101110001101000010000000101101001111100010000000110000001000000010100001010011011011010110000101101100011011000010000001001110011101010110110101100010011001010111001000101001 K
b0 I
b11111111011001100110011001100110011001100110011001100110011010 J
#210000
b10000000000000000000000000000000000000000000000000000 /
b10000000000000000000000000000000000000000000000000000 '
b10000000000000000000000000000000000000000000000000000 G
b10000000000000000000000000000000000000000000000000000 F
b10000000000000000000000000000000000000000000000000000 (
b10000000000000000000000000000000000000000000000000000 D
0&
b1000000000000000000000000000000000000000000000000000000000000 !
b1000000000000000000000000000000000000000000000000000000000000 4
b0 5
b1000000000000000000000000000000000000000000000000000000000000 2
b1000000000000000000000000000000000000000000000000000000000000 3
0%
b111100 .
b111100 @
b100000000000000000000000000000000000000000000000000000000000000000000000000000000000000000000000000000000000000000000 6
b10000000000000000000000000000000000000000000000000000 +
b10000000000000000000000000000000000000000000000000000 >
b10000111011 =
1?
b0 <
b100001110110000000000000000000000000000000000000000000000000000 "
b100001110110000000000000000000000000000000000000000000000000000 #
b100001110110000000000000000000000000000000000000000000000000000 7
b1010100011001010111001101110100001000000011000100110001001110100010000000110010010111100011011000110000001000000010100001001100011000010111001001100111011001010010000001001110011101010110110101100010011001010111001000101001 K
b1000000000000000000000000000000000000000000000000000000000000 I
b100001110110000000000000000000000000000000000000000000000000000 J
#230000
b1111000000000000000000000000000000000000000000000000000000000000 !
b1111000000000000000000000000000000000000000000000000000000000000 4
1$
1;
b1100001110110000000000000000000000000000000000000000000000000000 "
b1100001110110000000000000000000000000000000000000000000000000000 #
b1100001110110000000000000000000000000000000000000000000000000000 7
b101010001100101011100110111010000100000001100010011001000111010001000000010110100110010010111100011011000110000001000000010100001001110011001010110011101100001011101000110100101110110011001010010000001001100011000010111001001100111011001010010000001001110011101010110110101100010011001010111001000101001 K
b1111000000000000000000000000000000000000000000000000000000000000 I
b1100001110110000000000000000000000000000000000000000000000000000 J
